{
  "id": "chinese_heritage_073_1",
  "name": "chinese_heritage_073_1",
  "picture_id": "chinese_heritage_073",
  "size": 10,
  "difficulty": "easy",
  "solution": [
    [
      0,
      0,
      0,
      0,
      0,
      0,
      0,
      0,
      0,
      0
    ],
    [
      0,
      0,
      0,
      0,
      0,
      0,
      0,
      0,
      0,
      0
    ],
    [
      0,
      0,
      0,
      0,
      0,
      1,
      0,
      0,
      0,
      0
    ],
    [
      0,
      0,
      0,
      0,
      0,
      1,
      0,
      0,
      0,
      0
    ],
    [
      0,
      0,
      1,
      0,
      1,
      1,
      0,
      1,
      1,
      0
    ],
    [
      0,
      1,
      1,
      0,
      1,
      1,
      0,
      1,
      1,
      1
    ],
    [
      1,
      1,
      1,
      0,
      1,
      1,
      1,
      1,
      1,
      1
    ],
    [
      1,
      1,
      1,
      0,
      1,
      1,
      1,
      1,
      1,
      1
    ],
    [
      1,
      1,
      0,
      0,
      1,
      1,
      1,
      1,
      1,
      1
    ],
    [
      1,
      1,
      1,
      1,
      1,
      1,
      0,
      1,
      1,
      1
    ]
  ],
  "row_clues": [
    [
      0
    ],
    [
      0
    ],
    [
      1
    ],
    [
      1
    ],
    [
      1,
      2,
      2
    ],
    [
      2,
      2,
      3
    ],
    [
      3,
      6
    ],
    [
      3,
      6
    ],
    [
      2,
      6
    ],
    [
      6,
      3
    ]
  ],
  "col_clues": [
    [
      4
    ],
    [
      5
    ],
    [
      4,
      1
    ],
    [
      1
    ],
    [
      6
    ],
    [
      8
    ],
    [
      3
    ],
    [
      6
    ],
    [
      6
    ],
    [
      5
    ]
  ],
  "hint_cells": [],
  "source_rect": {
    "x": 832,
    "y": 0,
    "width": 832,
    "height": 832
  }
}