{
  "id": "war_military_069_1",
  "name": "war_military_069_1",
  "picture_id": "war_military_069",
  "size": 10,
  "difficulty": "easy",
  "solution": [
    [
      1,
      1,
      1,
      1,
      1,
      1,
      1,
      1,
      1,
      1
    ],
    [
      1,
      1,
      1,
      1,
      1,
      1,
      1,
      1,
      1,
      1
    ],
    [
      1,
      1,
      1,
      1,
      1,
      1,
      1,
      1,
      1,
      1
    ],
    [
      1,
      0,
      0,
      1,
      1,
      1,
      1,
      1,
      1,
      1
    ],
    [
      1,
      0,
      0,
      0,
      1,
      0,
      1,
      0,
      1,
      1
    ],
    [
      0,
      0,
      0,
      1,
      0,
      0,
      1,
      1,
      1,
      1
    ],
    [
      0,
      0,
      0,
      1,
      1,
      0,
      0,
      1,
      1,
      1
    ],
    [
      1,
      0,
      0,
      0,
      0,
      1,
      1,
      0,
      0,
      0
    ],
    [
      1,
      1,
      1,
      1,
      1,
      0,
      0,
      0,
      1,
      1
    ],
    [
      1,
      1,
      0,
      0,
      0,
      0,
      0,
      0,
      0,
      0
    ]
  ],
  "row_clues": [
    [
      10
    ],
    [
      10
    ],
    [
      10
    ],
    [
      1,
      7
    ],
    [
      1,
      1,
      1,
      2
    ],
    [
      1,
      4
    ],
    [
      2,
      3
    ],
    [
      1,
      2
    ],
    [
      5,
      2
    ],
    [
      2
    ]
  ],
  "col_clues": [
    [
      5,
      3
    ],
    [
      3,
      2
    ],
    [
      3,
      1
    ],
    [
      4,
      2,
      1
    ],
    [
      5,
      1,
      1
    ],
    [
      4,
      1
    ],
    [
      6,
      1
    ],
    [
      4,
      2
    ],
    [
      7,
      1
    ],
    [
      7,
      1
    ]
  ],
  "hint_cells": [],
  "source_rect": {
    "x": 426,
    "y": 0,
    "width": 426,
    "height": 426
  }
}