{
  "id": "economic_trade_030_4",
  "name": "economic_trade_030_4",
  "picture_id": "economic_trade_030",
  "size": 10,
  "difficulty": "easy",
  "solution": [
    [
      0,
      0,
      0,
      0,
      0,
      0,
      0,
      1,
      1,
      1
    ],
    [
      0,
      0,
      0,
      0,
      0,
      0,
      0,
      1,
      1,
      1
    ],
    [
      0,
      0,
      0,
      0,
      0,
      0,
      0,
      1,
      1,
      1
    ],
    [
      0,
      0,
      0,
      0,
      1,
      1,
      1,
      1,
      1,
      1
    ],
    [
      0,
      1,
      1,
      1,
      1,
      1,
      1,
      1,
      1,
      1
    ],
    [
      1,
      1,
      1,
      1,
      1,
      1,
      1,
      0,
      0,
      1
    ],
    [
      1,
      1,
      1,
      1,
      0,
      1,
      1,
      1,
      0,
      0
    ],
    [
      1,
      1,
      1,
      1,
      1,
      1,
      0,
      1,
      0,
      0
    ],
    [
      0,
      1,
      1,
      1,
      1,
      0,
      0,
      1,
      0,
      0
    ],
    [
      0,
      0,
      0,
      0,
      1,
      1,
      1,
      0,
      0,
      0
    ]
  ],
  "row_clues": [
    [
      3
    ],
    [
      3
    ],
    [
      3
    ],
    [
      6
    ],
    [
      9
    ],
    [
      7,
      1
    ],
    [
      4,
      3
    ],
    [
      6,
      1
    ],
    [
      4,
      1
    ],
    [
      3
    ]
  ],
  "col_clues": [
    [
      3
    ],
    [
      5
    ],
    [
      5
    ],
    [
      5
    ],
    [
      3,
      3
    ],
    [
      5,
      1
    ],
    [
      4,
      1
    ],
    [
      5,
      3
    ],
    [
      5
    ],
    [
      6
    ]
  ],
  "hint_cells": [],
  "source_rect": {
    "x": 426,
    "y": 426,
    "width": 426,
    "height": 426
  }
}