{
  "id": "africa_america_civilization_018_1",
  "name": "africa_america_civilization_018_1",
  "picture_id": "africa_america_civilization_018",
  "size": 5,
  "difficulty": "tutorial",
  "solution": [
    [
      0,
      0,
      0,
      0,
      0
    ],
    [
      0,
      0,
      0,
      0,
      0
    ],
    [
      0,
      0,
      1,
      1,
      0
    ],
    [
      0,
      0,
      1,
      1,
      0
    ],
    [
      0,
      0,
      1,
      1,
      0
    ]
  ],
  "row_clues": [
    [
      0
    ],
    [
      0
    ],
    [
      2
    ],
    [
      2
    ],
    [
      2
    ]
  ],
  "col_clues": [
    [
      0
    ],
    [
      0
    ],
    [
      3
    ],
    [
      3
    ],
    [
      0
    ]
  ],
  "hint_cells": [],
  "source_rect": {
    "x": 426,
    "y": 0,
    "width": 426,
    "height": 426
  }
}