{
  "id": "world_history_074_1",
  "name": "world_history_074_1",
  "picture_id": "world_history_074",
  "size": 10,
  "difficulty": "easy",
  "solution": [
    [
      1,
      1,
      1,
      1,
      1,
      1,
      1,
      1,
      1,
      1
    ],
    [
      1,
      1,
      1,
      1,
      1,
      1,
      1,
      1,
      1,
      1
    ],
    [
      1,
      1,
      1,
      1,
      1,
      1,
      1,
      1,
      1,
      1
    ],
    [
      1,
      1,
      1,
      1,
      1,
      1,
      1,
      1,
      1,
      1
    ],
    [
      1,
      1,
      1,
      1,
      1,
      1,
      1,
      0,
      0,
      0
    ],
    [
      0,
      1,
      1,
      1,
      1,
      0,
      1,
      1,
      1,
      1
    ],
    [
      0,
      0,
      0,
      0,
      0,
      0,
      0,
      0,
      1,
      1
    ],
    [
      0,
      0,
      0,
      0,
      0,
      0,
      0,
      0,
      0,
      0
    ],
    [
      0,
      0,
      0,
      0,
      0,
      0,
      0,
      0,
      0,
      0
    ],
    [
      0,
      0,
      0,
      0,
      0,
      0,
      0,
      0,
      0,
      0
    ]
  ],
  "row_clues": [
    [
      10
    ],
    [
      10
    ],
    [
      10
    ],
    [
      10
    ],
    [
      7
    ],
    [
      4,
      4
    ],
    [
      2
    ],
    [
      0
    ],
    [
      0
    ],
    [
      0
    ]
  ],
  "col_clues": [
    [
      5
    ],
    [
      6
    ],
    [
      6
    ],
    [
      6
    ],
    [
      6
    ],
    [
      5
    ],
    [
      6
    ],
    [
      4,
      1
    ],
    [
      4,
      2
    ],
    [
      4,
      2
    ]
  ],
  "hint_cells": [],
  "source_rect": {
    "x": 426,
    "y": 0,
    "width": 426,
    "height": 426
  }
}