{
	"id": "world_heritage_030_0",
	"name": "分块0",
	"picture_id": "world_heritage_030",
	"size": {
		"rows": 5,
		"cols": 5
	},
	"difficulty": "tutorial",
	"row_clues": [
		[
			1
		],
		[
			1
		],
		[
			1
		],
		[
			1
		],
		[
			1
		]
	],
	"col_clues": [
		[
			1
		],
		[
			1
		],
		[
			1
		],
		[
			1
		],
		[
			1
		]
	],
	"solution": [
		[
			0,
			0,
			0,
			1,
			0
		],
		[
			0,
			0,
			1,
			0,
			0
		],
		[
			1,
			0,
			0,
			0,
			0
		],
		[
			0,
			1,
			0,
			0,
			0
		],
		[
			0,
			0,
			0,
			0,
			1
		]
	],
	"hint_cells": [
		[
			0,
			0
		],
		[
			0,
			1
		],
		[
			0,
			2
		],
		[
			0,
			4
		],
		[
			1,
			0
		],
		[
			1,
			1
		],
		[
			1,
			4
		],
		[
			2,
			1
		],
		[
			2,
			4
		],
		[
			3,
			4
		]
	],
	"source_rect": {
		"x": 0,
		"y": 0,
		"w": 426,
		"h": 426
	}
}