{
  "id": "world_heritage_004_3",
  "name": "world_heritage_004_3",
  "picture_id": "world_heritage_004",
  "size": 5,
  "difficulty": "tutorial",
  "solution": [
    [
      0,
      1,
      1,
      1,
      1
    ],
    [
      0,
      1,
      0,
      0,
      1
    ],
    [
      0,
      1,
      0,
      1,
      1
    ],
    [
      0,
      1,
      0,
      0,
      1
    ],
    [
      0,
      0,
      0,
      1,
      1
    ]
  ],
  "row_clues": [
    [
      4
    ],
    [
      1,
      1
    ],
    [
      1,
      2
    ],
    [
      1,
      1
    ],
    [
      2
    ]
  ],
  "col_clues": [
    [
      0
    ],
    [
      4
    ],
    [
      1
    ],
    [
      1,
      1,
      1
    ],
    [
      5
    ]
  ],
  "hint_cells": [],
  "source_rect": {
    "x": 0,
    "y": 426,
    "width": 426,
    "height": 426
  }
}