{
  "id": "european_civilization_046_2",
  "name": "european_civilization_046_2",
  "picture_id": "european_civilization_046",
  "size": 5,
  "difficulty": "tutorial",
  "solution": [
    [
      0,
      0,
      0,
      0,
      0
    ],
    [
      1,
      1,
      1,
      1,
      1
    ],
    [
      1,
      1,
      1,
      1,
      1
    ],
    [
      0,
      0,
      0,
      0,
      0
    ],
    [
      0,
      0,
      0,
      0,
      0
    ]
  ],
  "row_clues": [
    [
      0
    ],
    [
      5
    ],
    [
      5
    ],
    [
      0
    ],
    [
      0
    ]
  ],
  "col_clues": [
    [
      2
    ],
    [
      2
    ],
    [
      2
    ],
    [
      2
    ],
    [
      2
    ]
  ],
  "hint_cells": [],
  "source_rect": {
    "x": 852,
    "y": 0,
    "width": 426,
    "height": 426
  }
}