{
  "id": "archaeology_007_0",
  "name": "archaeology_007_0",
  "picture_id": "archaeology_007",
  "size": 10,
  "difficulty": "easy",
  "subject": "density_gradient",
  "solution": [
    [
      0,
      0,
      0,
      0,
      1,
      0,
      0,
      0,
      0,
      0
    ],
    [
      0,
      0,
      1,
      0,
      0,
      0,
      0,
      0,
      0,
      1
    ],
    [
      0,
      0,
      1,
      1,
      1,
      0,
      1,
      0,
      1,
      0
    ],
    [
      0,
      0,
      1,
      1,
      1,
      0,
      1,
      1,
      1,
      0
    ],
    [
      0,
      0,
      1,
      1,
      1,
      1,
      1,
      0,
      0,
      0
    ],
    [
      0,
      0,
      1,
      1,
      1,
      0,
      1,
      0,
      0,
      0
    ],
    [
      1,
      1,
      1,
      1,
      1,
      1,
      1,
      1,
      0,
      0
    ],
    [
      0,
      0,
      1,
      0,
      1,
      0,
      1,
      1,
      0,
      0
    ],
    [
      0,
      0,
      0,
      1,
      1,
      0,
      1,
      1,
      0,
      0
    ],
    [
      0,
      0,
      0,
      0,
      0,
      0,
      0,
      0,
      1,
      0
    ]
  ],
  "row_clues": [
    [
      1
    ],
    [
      1,
      1
    ],
    [
      3,
      1,
      1
    ],
    [
      3,
      3
    ],
    [
      5
    ],
    [
      3,
      1
    ],
    [
      8
    ],
    [
      1,
      1,
      2
    ],
    [
      2,
      2
    ],
    [
      1
    ]
  ],
  "col_clues": [
    [
      1
    ],
    [
      1
    ],
    [
      7
    ],
    [
      5,
      1
    ],
    [
      1,
      7
    ],
    [
      1,
      1
    ],
    [
      7
    ],
    [
      1,
      3
    ],
    [
      2,
      1
    ],
    [
      1
    ]
  ],
  "hint_cells": [
    [
      2,
      9
    ],
    [
      2,
      1
    ],
    [
      9,
      1
    ],
    [
      9,
      9
    ],
    [
      9,
      0
    ]
  ],
  "reasoning_steps": 68,
  "source_rect": {
    "x": 0,
    "y": 0,
    "width": 832,
    "height": 832
  }
}